dycodebase/__init__.py
dycodebase/model/__init__.py
dycodebase/model/components/__init__.py
dycodebase/model/components/squeeze_excite.py
dycodebase-0.0.5.dist-info/METADATA
dycodebase-0.0.5.dist-info/WHEEL
dycodebase-0.0.5.dist-info/top_level.txt
dycodebase-0.0.5.dist-info/RECORD
