Metadata-Version: 2.1
Name: dycodebase
Version: 0.0.5
Summary: CodeBase of important Functions
Author: Devin De Silva
Author-email: devin@irononetech.com
Keywords: python,codebase
Classifier: Development Status :: 3 - Alpha
Classifier: Intended Audience :: Developers
Classifier: Programming Language :: Python :: 3.9
Classifier: Operating System :: MacOS :: MacOS X
Classifier: Operating System :: Microsoft :: Windows
Requires-Dist: tensorflow
